[
  {
    "type": "Economy",
    "company": "RideEasy",
    "capacity": 4,
    "price_per_km": 10,
    "rating": 4.3,
    "availability": "24/7",
    "description": "Budget-friendly and reliable city rides.",
    "image": "https://source.unsplash.com/400x250/?economy,taxi&sig=1",
    "driver_name": "Amit Sharma",
    "driver_phone": "+91-98765-43210"
  },
  {
    "type": "Premium",
    "company": "LuxCab",
    "capacity": 4,
    "price_per_km": 18,
    "rating": 4.7,
    "availability": "6am - 11pm",
    "description": "Premium comfort with top-rated drivers.",
    "image": "https://source.unsplash.com/400x250/?premium,taxi&sig=2",
    "driver_name": "Ravi Singh",
    "driver_phone": "+91-99887-77665"
  },
  {
    "type": "SUV",
    "company": "GoSUV",
    "capacity": 6,
    "price_per_km": 15,
    "rating": 4.5,
    "availability": "24/7",
    "description": "Spacious and ideal for road trips.",
    "image": "https://source.unsplash.com/400x250/?suv,taxi&sig=3",
    "driver_name": "Sunil Mehta",
    "driver_phone": "+91-93456-18923"
  },
  {
    "type": "Shared",
    "company": "Zoomy",
    "capacity": 3,
    "price_per_km": 7,
    "rating": 4.0,
    "availability": "Morning Only",
    "description": "Affordable shared rides for daily travel.",
    "image": "https://source.unsplash.com/400x250/?shared,taxi&sig=4",
    "driver_name": "Vijay Kumar",
    "driver_phone": "+91-90123-65432"
  },
  {
    "type": "Electric",
    "company": "GreenRide",
    "capacity": 4,
    "price_per_km": 9,
    "rating": 4.6,
    "availability": "24/7",
    "description": "Eco-friendly electric cabs for city trips.",
    "image": "https://source.unsplash.com/400x250/?electric,taxi&sig=5",
    "driver_name": "Karan Yadav",
    "driver_phone": "+91-90909-10101"
  },
  {
    "type": "Luxury",
    "company": "EliteDrive",
    "capacity": 4,
    "price_per_km": 22,
    "rating": 4.9,
    "availability": "7am - 10pm",
    "description": "Luxury class with premium features.",
    "image": "https://source.unsplash.com/400x250/?luxury,taxi&sig=6",
    "driver_name": "Ramesh Patel",
    "driver_phone": "+91-93210-76543"
  },
  {
    "type": "SUV",
    "company": "QuickMove",
    "capacity": 7,
    "price_per_km": 16,
    "rating": 4.4,
    "availability": "Night Only",
    "description": "Comfortable for long trips and groups.",
    "image": "https://source.unsplash.com/400x250/?suv,taxi&sig=7",
    "driver_name": "Anil Joshi",
    "driver_phone": "+91-90785-44321"
  },
  {
    "type": "Electric",
    "company": "Zoomy",
    "capacity": 4,
    "price_per_km": 11,
    "rating": 4.5,
    "availability": "6am - 11pm",
    "description": "Clean and quiet electric ride.",
    "image": "https://source.unsplash.com/400x250/?electric,taxi&sig=8",
    "driver_name": "Mukesh Verma",
    "driver_phone": "+91-91234-12345"
  },
  {
    "type": "Economy",
    "company": "SafeWheels",
    "capacity": 4,
    "price_per_km": 9,
    "rating": 4.1,
    "availability": "24/7",
    "description": "Safe, budget rides with verified drivers.",
    "image": "https://source.unsplash.com/400x250/?budget,taxi&sig=9",
    "driver_name": "Sanjay Gupta",
    "driver_phone": "+91-98700-99888"
  },
  {
    "type": "Luxury",
    "company": "UrbanRide",
    "capacity": 4,
    "price_per_km": 20,
    "rating": 4.8,
    "availability": "7am - 11pm",
    "description": "Elegant interiors and smooth experience.",
    "image": "https://source.unsplash.com/400x250/?luxurycar,taxi&sig=10",
    "driver_name": "Ajay Pandey",
    "driver_phone": "+91-98888-12321"
  },
  {
    "type": "Premium",
    "company": "CityCab",
    "capacity": 4,
    "price_per_km": 17,
    "rating": 4.6,
    "availability": "6am - 10pm",
    "description": "Business-class cabs for quick transfers.",
    "image": "https://source.unsplash.com/400x250/?sedan,taxi&sig=11",
    "driver_name": "Rajat Kumar",
    "driver_phone": "+91-93456-70890"
  },
  {
    "type": "Shared",
    "company": "QuickShare",
    "capacity": 3,
    "price_per_km": 6,
    "rating": 3.9,
    "availability": "Morning Only",
    "description": "Easy ride-share with fast routes.",
    "image": "https://source.unsplash.com/400x250/?shared,taxi&sig=12",
    "driver_name": "Hemant Singh",
    "driver_phone": "+91-95050-11223"
  },
  {
    "type": "Electric",
    "company": "GreenZoom",
    "capacity": 4,
    "price_per_km": 10,
    "rating": 4.7,
    "availability": "24/7",
    "description": "Zero-emission cabs for clean city travel.",
    "image": "https://source.unsplash.com/400x250/?tesla,taxi&sig=13",
    "driver_name": "Dev Joshi",
    "driver_phone": "+91-98812-76543"
  },
  {
    "type": "SUV",
    "company": "RideMax",
    "capacity": 6,
    "price_per_km": 14,
    "rating": 4.3,
    "availability": "7am - 11pm",
    "description": "Bold and spacious with room for all.",
    "image": "https://source.unsplash.com/400x250/?jeep,taxi&sig=14",
    "driver_name": "Yogesh Mehta",
    "driver_phone": "+91-91111-66666"
  },
  {
    "type": "Economy",
    "company": "FastTrack",
    "capacity": 4,
    "price_per_km": 8,
    "rating": 4.0,
    "availability": "24/7",
    "description": "Fast, no-frills transportation service.",
    "image": "https://source.unsplash.com/400x250/?compact,taxi&sig=15",
    "driver_name": "Arun Verma",
    "driver_phone": "+91-92222-33333"
  }
]
